<?xml version="1.0" encoding="utf-8"?>
<helpItems schema="maml" xmlns="http://msh">
  <command:command xmlns:maml="http://schemas.microsoft.com/maml/2004/10" xmlns:command="http://schemas.microsoft.com/maml/dev/command/2004/10" xmlns:dev="http://schemas.microsoft.com/maml/dev/2004/10" xmlns:MSHelp="http://msdn.microsoft.com/mshelp">
    <command:details>
      <command:name>Get-ServiceOperation</command:name>
      <command:verb>Get</command:verb>
      <command:noun>ServiceOperation</command:noun>
      <maml:description>
        <maml:para></maml:para>
      </maml:description>
    </command:details>
    <maml:description>
      <maml:para>{{Fill in the Description}}</maml:para>
    </maml:description>
    <command:syntax>
      <command:syntaxItem>
        <maml:name>Get-ServiceOperation</maml:name>
        <command:parameter required="false" variableLength="true" globbing="false" pipelineInput="False" position="named" aliases="none">
          <maml:name>Filter</maml:name>
          <maml:Description>
            <maml:para>The filter in FIQL syntax used for the results.</maml:para>
          </maml:Description>
          <command:parameterValue required="true" variableLength="false">System.String</command:parameterValue>
          <dev:type>
            <maml:name>System.String</maml:name>
            <maml:uri />
          </dev:type>
          <dev:defaultValue>None</dev:defaultValue>
        </command:parameter>
        <command:parameter required="false" variableLength="true" globbing="false" pipelineInput="False" position="named" aliases="none">
          <maml:name>HttpPipelineAppend</maml:name>
          <maml:Description>
            <maml:para>SendAsync Pipeline Steps to be appended to the front of the pipeline</maml:para>
          </maml:Description>
          <command:parameterValue required="true" variableLength="false">Microsoft.Rest.ClientRuntime.SendAsyncStep[]</command:parameterValue>
          <dev:type>
            <maml:name>Microsoft.Rest.ClientRuntime.SendAsyncStep[]</maml:name>
            <maml:uri />
          </dev:type>
          <dev:defaultValue>None</dev:defaultValue>
        </command:parameter>
        <command:parameter required="false" variableLength="true" globbing="false" pipelineInput="False" position="named" aliases="none">
          <maml:name>HttpPipelinePrepend</maml:name>
          <maml:Description>
            <maml:para>SendAsync Pipeline Steps to be prepended to the front of the pipeline</maml:para>
          </maml:Description>
          <command:parameterValue required="true" variableLength="false">Microsoft.Rest.ClientRuntime.SendAsyncStep[]</command:parameterValue>
          <dev:type>
            <maml:name>Microsoft.Rest.ClientRuntime.SendAsyncStep[]</maml:name>
            <maml:uri />
          </dev:type>
          <dev:defaultValue>None</dev:defaultValue>
        </command:parameter>
        <command:parameter required="false" variableLength="true" globbing="false" pipelineInput="False" position="named" aliases="none">
          <maml:name>Kind</maml:name>
          <maml:Description>
            <maml:para>The kind name</maml:para>
          </maml:Description>
          <command:parameterValue required="true" variableLength="false">System.String</command:parameterValue>
          <dev:type>
            <maml:name>System.String</maml:name>
            <maml:uri />
          </dev:type>
          <dev:defaultValue>None</dev:defaultValue>
        </command:parameter>
        <command:parameter required="false" variableLength="true" globbing="false" pipelineInput="False" position="named" aliases="none">
          <maml:name>Length</maml:name>
          <maml:Description>
            <maml:para>The number of records to retrieve relative to the offset</maml:para>
          </maml:Description>
          <command:parameterValue required="true" variableLength="false">System.Int32</command:parameterValue>
          <dev:type>
            <maml:name>System.Int32</maml:name>
            <maml:uri />
          </dev:type>
          <dev:defaultValue>0</dev:defaultValue>
        </command:parameter>
        <command:parameter required="false" variableLength="true" globbing="false" pipelineInput="False" position="named" aliases="none">
          <maml:name>Offset</maml:name>
          <maml:Description>
            <maml:para>Offset from the start of the entity list</maml:para>
          </maml:Description>
          <command:parameterValue required="true" variableLength="false">System.Int32</command:parameterValue>
          <dev:type>
            <maml:name>System.Int32</maml:name>
            <maml:uri />
          </dev:type>
          <dev:defaultValue>0</dev:defaultValue>
        </command:parameter>
        <command:parameter required="false" variableLength="true" globbing="false" pipelineInput="False" position="named" aliases="none">
          <maml:name>Proxy</maml:name>
          <maml:Description>
            <maml:para>The URI for the proxy server to use</maml:para>
          </maml:Description>
          <command:parameterValue required="true" variableLength="false">System.Uri</command:parameterValue>
          <dev:type>
            <maml:name>System.Uri</maml:name>
            <maml:uri />
          </dev:type>
          <dev:defaultValue>None</dev:defaultValue>
        </command:parameter>
        <command:parameter required="false" variableLength="true" globbing="false" pipelineInput="False" position="named" aliases="none">
          <maml:name>ProxyCredential</maml:name>
          <maml:Description>
            <maml:para>Credentials for a proxy server to use for the remote call</maml:para>
          </maml:Description>
          <command:parameterValue required="true" variableLength="false">System.Management.Automation.PSCredential</command:parameterValue>
          <dev:type>
            <maml:name>System.Management.Automation.PSCredential</maml:name>
            <maml:uri />
          </dev:type>
          <dev:defaultValue>None</dev:defaultValue>
        </command:parameter>
        <command:parameter required="false" variableLength="true" globbing="false" pipelineInput="False" position="named" aliases="none">
          <maml:name>ProxyUseDefaultCredentials</maml:name>
          <maml:Description>
            <maml:para>Use the default credentials for the proxy</maml:para>
          </maml:Description>
          <dev:type>
            <maml:name>System.Management.Automation.SwitchParameter</maml:name>
            <maml:uri />
          </dev:type>
          <dev:defaultValue>False</dev:defaultValue>
        </command:parameter>
        <command:parameter required="false" variableLength="true" globbing="false" pipelineInput="False" position="named" aliases="none">
          <maml:name>SortAttribute</maml:name>
          <maml:Description>
            <maml:para>The attribute to perform sort on</maml:para>
          </maml:Description>
          <command:parameterValue required="true" variableLength="false">System.String</command:parameterValue>
          <dev:type>
            <maml:name>System.String</maml:name>
            <maml:uri />
          </dev:type>
          <dev:defaultValue>None</dev:defaultValue>
        </command:parameter>
        <command:parameter required="false" variableLength="true" globbing="false" pipelineInput="False" position="named" aliases="cf">
          <maml:name>Confirm</maml:name>
          <maml:Description>
            <maml:para>Prompts you for confirmation before running the cmdlet.</maml:para>
          </maml:Description>
          <dev:type>
            <maml:name>System.Management.Automation.SwitchParameter</maml:name>
            <maml:uri />
          </dev:type>
          <dev:defaultValue>False</dev:defaultValue>
        </command:parameter>
        <command:parameter required="false" variableLength="true" globbing="false" pipelineInput="False" position="named" aliases="wi">
          <maml:name>WhatIf</maml:name>
          <maml:Description>
            <maml:para>Shows what would happen if the cmdlet runs. The cmdlet is not run.</maml:para>
          </maml:Description>
          <dev:type>
            <maml:name>System.Management.Automation.SwitchParameter</maml:name>
            <maml:uri />
          </dev:type>
          <dev:defaultValue>False</dev:defaultValue>
        </command:parameter>
      </command:syntaxItem>
      <command:syntaxItem>
        <maml:name>Get-ServiceOperation</maml:name>
        <command:parameter required="true" variableLength="true" globbing="false" pipelineInput="True (ByValue)" position="named" aliases="none">
          <maml:name>GetEntitiesRequest</maml:name>
          <maml:Description>
            <maml:para>All api calls that return a list will have this metadata block as input</maml:para>
          </maml:Description>
          <command:parameterValue required="true" variableLength="false">Sample.API.Models.IAccessControlPolicyListMetadata</command:parameterValue>
          <dev:type>
            <maml:name>Sample.API.Models.IAccessControlPolicyListMetadata</maml:name>
            <maml:uri />
          </dev:type>
          <dev:defaultValue>None</dev:defaultValue>
        </command:parameter>
        <command:parameter required="false" variableLength="true" globbing="false" pipelineInput="False" position="named" aliases="none">
          <maml:name>HttpPipelineAppend</maml:name>
          <maml:Description>
            <maml:para>SendAsync Pipeline Steps to be appended to the front of the pipeline</maml:para>
          </maml:Description>
          <command:parameterValue required="true" variableLength="false">Microsoft.Rest.ClientRuntime.SendAsyncStep[]</command:parameterValue>
          <dev:type>
            <maml:name>Microsoft.Rest.ClientRuntime.SendAsyncStep[]</maml:name>
            <maml:uri />
          </dev:type>
          <dev:defaultValue>None</dev:defaultValue>
        </command:parameter>
        <command:parameter required="false" variableLength="true" globbing="false" pipelineInput="False" position="named" aliases="none">
          <maml:name>HttpPipelinePrepend</maml:name>
          <maml:Description>
            <maml:para>SendAsync Pipeline Steps to be prepended to the front of the pipeline</maml:para>
          </maml:Description>
          <command:parameterValue required="true" variableLength="false">Microsoft.Rest.ClientRuntime.SendAsyncStep[]</command:parameterValue>
          <dev:type>
            <maml:name>Microsoft.Rest.ClientRuntime.SendAsyncStep[]</maml:name>
            <maml:uri />
          </dev:type>
          <dev:defaultValue>None</dev:defaultValue>
        </command:parameter>
        <command:parameter required="false" variableLength="true" globbing="false" pipelineInput="False" position="named" aliases="none">
          <maml:name>Proxy</maml:name>
          <maml:Description>
            <maml:para>The URI for the proxy server to use</maml:para>
          </maml:Description>
          <command:parameterValue required="true" variableLength="false">System.Uri</command:parameterValue>
          <dev:type>
            <maml:name>System.Uri</maml:name>
            <maml:uri />
          </dev:type>
          <dev:defaultValue>None</dev:defaultValue>
        </command:parameter>
        <command:parameter required="false" variableLength="true" globbing="false" pipelineInput="False" position="named" aliases="none">
          <maml:name>ProxyCredential</maml:name>
          <maml:Description>
            <maml:para>Credentials for a proxy server to use for the remote call</maml:para>
          </maml:Description>
          <command:parameterValue required="true" variableLength="false">System.Management.Automation.PSCredential</command:parameterValue>
          <dev:type>
            <maml:name>System.Management.Automation.PSCredential</maml:name>
            <maml:uri />
          </dev:type>
          <dev:defaultValue>None</dev:defaultValue>
        </command:parameter>
        <command:parameter required="false" variableLength="true" globbing="false" pipelineInput="False" position="named" aliases="none">
          <maml:name>ProxyUseDefaultCredentials</maml:name>
          <maml:Description>
            <maml:para>Use the default credentials for the proxy</maml:para>
          </maml:Description>
          <dev:type>
            <maml:name>System.Management.Automation.SwitchParameter</maml:name>
            <maml:uri />
          </dev:type>
          <dev:defaultValue>False</dev:defaultValue>
        </command:parameter>
        <command:parameter required="false" variableLength="true" globbing="false" pipelineInput="False" position="named" aliases="cf">
          <maml:name>Confirm</maml:name>
          <maml:Description>
            <maml:para>Prompts you for confirmation before running the cmdlet.</maml:para>
          </maml:Description>
          <dev:type>
            <maml:name>System.Management.Automation.SwitchParameter</maml:name>
            <maml:uri />
          </dev:type>
          <dev:defaultValue>False</dev:defaultValue>
        </command:parameter>
        <command:parameter required="false" variableLength="true" globbing="false" pipelineInput="False" position="named" aliases="wi">
          <maml:name>WhatIf</maml:name>
          <maml:Description>
            <maml:para>Shows what would happen if the cmdlet runs. The cmdlet is not run.</maml:para>
          </maml:Description>
          <dev:type>
            <maml:name>System.Management.Automation.SwitchParameter</maml:name>
            <maml:uri />
          </dev:type>
          <dev:defaultValue>False</dev:defaultValue>
        </command:parameter>
      </command:syntaxItem>
    </command:syntax>
    <command:parameters>
      <command:parameter required="false" variableLength="true" globbing="false" pipelineInput="False" position="named" aliases="none">
        <maml:name>Filter</maml:name>
        <maml:Description>
          <maml:para>The filter in FIQL syntax used for the results.</maml:para>
        </maml:Description>
        <command:parameterValue required="true" variableLength="false">System.String</command:parameterValue>
        <dev:type>
          <maml:name>System.String</maml:name>
          <maml:uri />
        </dev:type>
        <dev:defaultValue>None</dev:defaultValue>
      </command:parameter>
      <command:parameter required="true" variableLength="true" globbing="false" pipelineInput="True (ByValue)" position="named" aliases="none">
        <maml:name>GetEntitiesRequest</maml:name>
        <maml:Description>
          <maml:para>All api calls that return a list will have this metadata block as input</maml:para>
        </maml:Description>
        <command:parameterValue required="true" variableLength="false">Sample.API.Models.IAccessControlPolicyListMetadata</command:parameterValue>
        <dev:type>
          <maml:name>Sample.API.Models.IAccessControlPolicyListMetadata</maml:name>
          <maml:uri />
        </dev:type>
        <dev:defaultValue>None</dev:defaultValue>
      </command:parameter>
      <command:parameter required="false" variableLength="true" globbing="false" pipelineInput="False" position="named" aliases="none">
        <maml:name>HttpPipelineAppend</maml:name>
        <maml:Description>
          <maml:para>SendAsync Pipeline Steps to be appended to the front of the pipeline</maml:para>
        </maml:Description>
        <command:parameterValue required="true" variableLength="false">Microsoft.Rest.ClientRuntime.SendAsyncStep[]</command:parameterValue>
        <dev:type>
          <maml:name>Microsoft.Rest.ClientRuntime.SendAsyncStep[]</maml:name>
          <maml:uri />
        </dev:type>
        <dev:defaultValue>None</dev:defaultValue>
      </command:parameter>
      <command:parameter required="false" variableLength="true" globbing="false" pipelineInput="False" position="named" aliases="none">
        <maml:name>HttpPipelinePrepend</maml:name>
        <maml:Description>
          <maml:para>SendAsync Pipeline Steps to be prepended to the front of the pipeline</maml:para>
        </maml:Description>
        <command:parameterValue required="true" variableLength="false">Microsoft.Rest.ClientRuntime.SendAsyncStep[]</command:parameterValue>
        <dev:type>
          <maml:name>Microsoft.Rest.ClientRuntime.SendAsyncStep[]</maml:name>
          <maml:uri />
        </dev:type>
        <dev:defaultValue>None</dev:defaultValue>
      </command:parameter>
      <command:parameter required="false" variableLength="true" globbing="false" pipelineInput="False" position="named" aliases="none">
        <maml:name>Kind</maml:name>
        <maml:Description>
          <maml:para>The kind name</maml:para>
        </maml:Description>
        <command:parameterValue required="true" variableLength="false">System.String</command:parameterValue>
        <dev:type>
          <maml:name>System.String</maml:name>
          <maml:uri />
        </dev:type>
        <dev:defaultValue>None</dev:defaultValue>
      </command:parameter>
      <command:parameter required="false" variableLength="true" globbing="false" pipelineInput="False" position="named" aliases="none">
        <maml:name>Length</maml:name>
        <maml:Description>
          <maml:para>The number of records to retrieve relative to the offset</maml:para>
        </maml:Description>
        <command:parameterValue required="true" variableLength="false">System.Int32</command:parameterValue>
        <dev:type>
          <maml:name>System.Int32</maml:name>
          <maml:uri />
        </dev:type>
        <dev:defaultValue>0</dev:defaultValue>
      </command:parameter>
      <command:parameter required="false" variableLength="true" globbing="false" pipelineInput="False" position="named" aliases="none">
        <maml:name>Offset</maml:name>
        <maml:Description>
          <maml:para>Offset from the start of the entity list</maml:para>
        </maml:Description>
        <command:parameterValue required="true" variableLength="false">System.Int32</command:parameterValue>
        <dev:type>
          <maml:name>System.Int32</maml:name>
          <maml:uri />
        </dev:type>
        <dev:defaultValue>0</dev:defaultValue>
      </command:parameter>
      <command:parameter required="false" variableLength="true" globbing="false" pipelineInput="False" position="named" aliases="none">
        <maml:name>Proxy</maml:name>
        <maml:Description>
          <maml:para>The URI for the proxy server to use</maml:para>
        </maml:Description>
        <command:parameterValue required="true" variableLength="false">System.Uri</command:parameterValue>
        <dev:type>
          <maml:name>System.Uri</maml:name>
          <maml:uri />
        </dev:type>
        <dev:defaultValue>None</dev:defaultValue>
      </command:parameter>
      <command:parameter required="false" variableLength="true" globbing="false" pipelineInput="False" position="named" aliases="none">
        <maml:name>ProxyCredential</maml:name>
        <maml:Description>
          <maml:para>Credentials for a proxy server to use for the remote call</maml:para>
        </maml:Description>
        <command:parameterValue required="true" variableLength="false">System.Management.Automation.PSCredential</command:parameterValue>
        <dev:type>
          <maml:name>System.Management.Automation.PSCredential</maml:name>
          <maml:uri />
        </dev:type>
        <dev:defaultValue>None</dev:defaultValue>
      </command:parameter>
      <command:parameter required="false" variableLength="true" globbing="false" pipelineInput="False" position="named" aliases="none">
        <maml:name>ProxyUseDefaultCredentials</maml:name>
        <maml:Description>
          <maml:para>Use the default credentials for the proxy</maml:para>
        </maml:Description>
        <command:parameterValue required="true" variableLength="false">System.Management.Automation.SwitchParameter</command:parameterValue>
        <dev:type>
          <maml:name>System.Management.Automation.SwitchParameter</maml:name>
          <maml:uri />
        </dev:type>
        <dev:defaultValue>False</dev:defaultValue>
      </command:parameter>
      <command:parameter required="false" variableLength="true" globbing="false" pipelineInput="False" position="named" aliases="none">
        <maml:name>SortAttribute</maml:name>
        <maml:Description>
          <maml:para>The attribute to perform sort on</maml:para>
        </maml:Description>
        <command:parameterValue required="true" variableLength="false">System.String</command:parameterValue>
        <dev:type>
          <maml:name>System.String</maml:name>
          <maml:uri />
        </dev:type>
        <dev:defaultValue>None</dev:defaultValue>
      </command:parameter>
      <command:parameter required="false" variableLength="true" globbing="false" pipelineInput="False" position="named" aliases="cf">
        <maml:name>Confirm</maml:name>
        <maml:Description>
          <maml:para>Prompts you for confirmation before running the cmdlet.</maml:para>
        </maml:Description>
        <command:parameterValue required="true" variableLength="false">System.Management.Automation.SwitchParameter</command:parameterValue>
        <dev:type>
          <maml:name>System.Management.Automation.SwitchParameter</maml:name>
          <maml:uri />
        </dev:type>
        <dev:defaultValue>False</dev:defaultValue>
      </command:parameter>
      <command:parameter required="false" variableLength="true" globbing="false" pipelineInput="False" position="named" aliases="wi">
        <maml:name>WhatIf</maml:name>
        <maml:Description>
          <maml:para>Shows what would happen if the cmdlet runs. The cmdlet is not run.</maml:para>
        </maml:Description>
        <command:parameterValue required="true" variableLength="false">System.Management.Automation.SwitchParameter</command:parameterValue>
        <dev:type>
          <maml:name>System.Management.Automation.SwitchParameter</maml:name>
          <maml:uri />
        </dev:type>
        <dev:defaultValue>False</dev:defaultValue>
      </command:parameter>
    </command:parameters>
    <command:inputTypes />
    <command:returnValues />
    <maml:alertSet>
      <maml:alert>
        <maml:para></maml:para>
      </maml:alert>
    </maml:alertSet>
    <command:examples>
      <command:example>
        <maml:title>-------------------------- Example 1 --------------------------</maml:title>
        <dev:code>PS C:\&gt; {{ Add example code here }}</dev:code>
        <dev:remarks>
          <maml:para>{{ Add example description here }}</maml:para>
        </dev:remarks>
      </command:example>
    </command:examples>
    <command:relatedLinks />
  </command:command>
  <command:command xmlns:maml="http://schemas.microsoft.com/maml/2004/10" xmlns:command="http://schemas.microsoft.com/maml/dev/command/2004/10" xmlns:dev="http://schemas.microsoft.com/maml/dev/2004/10" xmlns:MSHelp="http://msdn.microsoft.com/mshelp">
    <command:details>
      <command:name>Invoke-UserService</command:name>
      <command:verb>Invoke</command:verb>
      <command:noun>UserService</command:noun>
      <maml:description>
        <maml:para></maml:para>
      </maml:description>
    </command:details>
    <maml:description>
      <maml:para>{{Fill in the Description}}</maml:para>
    </maml:description>
    <command:syntax>
      <command:syntaxItem>
        <maml:name>Invoke-UserService</maml:name>
        <command:parameter required="false" variableLength="true" globbing="false" pipelineInput="False" position="named" aliases="none">
          <maml:name>HttpPipelineAppend</maml:name>
          <maml:Description>
            <maml:para>SendAsync Pipeline Steps to be appended to the front of the pipeline</maml:para>
          </maml:Description>
          <command:parameterValue required="true" variableLength="false">Microsoft.Rest.ClientRuntime.SendAsyncStep[]</command:parameterValue>
          <dev:type>
            <maml:name>Microsoft.Rest.ClientRuntime.SendAsyncStep[]</maml:name>
            <maml:uri />
          </dev:type>
          <dev:defaultValue>None</dev:defaultValue>
        </command:parameter>
        <command:parameter required="false" variableLength="true" globbing="false" pipelineInput="False" position="named" aliases="none">
          <maml:name>HttpPipelinePrepend</maml:name>
          <maml:Description>
            <maml:para>SendAsync Pipeline Steps to be prepended to the front of the pipeline</maml:para>
          </maml:Description>
          <command:parameterValue required="true" variableLength="false">Microsoft.Rest.ClientRuntime.SendAsyncStep[]</command:parameterValue>
          <dev:type>
            <maml:name>Microsoft.Rest.ClientRuntime.SendAsyncStep[]</maml:name>
            <maml:uri />
          </dev:type>
          <dev:defaultValue>None</dev:defaultValue>
        </command:parameter>
        <command:parameter required="false" variableLength="true" globbing="false" pipelineInput="False" position="named" aliases="none">
          <maml:name>Proxy</maml:name>
          <maml:Description>
            <maml:para>The URI for the proxy server to use</maml:para>
          </maml:Description>
          <command:parameterValue required="true" variableLength="false">System.Uri</command:parameterValue>
          <dev:type>
            <maml:name>System.Uri</maml:name>
            <maml:uri />
          </dev:type>
          <dev:defaultValue>None</dev:defaultValue>
        </command:parameter>
        <command:parameter required="false" variableLength="true" globbing="false" pipelineInput="False" position="named" aliases="none">
          <maml:name>ProxyCredential</maml:name>
          <maml:Description>
            <maml:para>Credentials for a proxy server to use for the remote call</maml:para>
          </maml:Description>
          <command:parameterValue required="true" variableLength="false">System.Management.Automation.PSCredential</command:parameterValue>
          <dev:type>
            <maml:name>System.Management.Automation.PSCredential</maml:name>
            <maml:uri />
          </dev:type>
          <dev:defaultValue>None</dev:defaultValue>
        </command:parameter>
        <command:parameter required="false" variableLength="true" globbing="false" pipelineInput="False" position="named" aliases="none">
          <maml:name>ProxyUseDefaultCredentials</maml:name>
          <maml:Description>
            <maml:para>Use the default credentials for the proxy</maml:para>
          </maml:Description>
          <dev:type>
            <maml:name>System.Management.Automation.SwitchParameter</maml:name>
            <maml:uri />
          </dev:type>
          <dev:defaultValue>False</dev:defaultValue>
        </command:parameter>
      </command:syntaxItem>
    </command:syntax>
    <command:parameters>
      <command:parameter required="false" variableLength="true" globbing="false" pipelineInput="False" position="named" aliases="none">
        <maml:name>HttpPipelineAppend</maml:name>
        <maml:Description>
          <maml:para>SendAsync Pipeline Steps to be appended to the front of the pipeline</maml:para>
        </maml:Description>
        <command:parameterValue required="true" variableLength="false">Microsoft.Rest.ClientRuntime.SendAsyncStep[]</command:parameterValue>
        <dev:type>
          <maml:name>Microsoft.Rest.ClientRuntime.SendAsyncStep[]</maml:name>
          <maml:uri />
        </dev:type>
        <dev:defaultValue>None</dev:defaultValue>
      </command:parameter>
      <command:parameter required="false" variableLength="true" globbing="false" pipelineInput="False" position="named" aliases="none">
        <maml:name>HttpPipelinePrepend</maml:name>
        <maml:Description>
          <maml:para>SendAsync Pipeline Steps to be prepended to the front of the pipeline</maml:para>
        </maml:Description>
        <command:parameterValue required="true" variableLength="false">Microsoft.Rest.ClientRuntime.SendAsyncStep[]</command:parameterValue>
        <dev:type>
          <maml:name>Microsoft.Rest.ClientRuntime.SendAsyncStep[]</maml:name>
          <maml:uri />
        </dev:type>
        <dev:defaultValue>None</dev:defaultValue>
      </command:parameter>
      <command:parameter required="false" variableLength="true" globbing="false" pipelineInput="False" position="named" aliases="none">
        <maml:name>Proxy</maml:name>
        <maml:Description>
          <maml:para>The URI for the proxy server to use</maml:para>
        </maml:Description>
        <command:parameterValue required="true" variableLength="false">System.Uri</command:parameterValue>
        <dev:type>
          <maml:name>System.Uri</maml:name>
          <maml:uri />
        </dev:type>
        <dev:defaultValue>None</dev:defaultValue>
      </command:parameter>
      <command:parameter required="false" variableLength="true" globbing="false" pipelineInput="False" position="named" aliases="none">
        <maml:name>ProxyCredential</maml:name>
        <maml:Description>
          <maml:para>Credentials for a proxy server to use for the remote call</maml:para>
        </maml:Description>
        <command:parameterValue required="true" variableLength="false">System.Management.Automation.PSCredential</command:parameterValue>
        <dev:type>
          <maml:name>System.Management.Automation.PSCredential</maml:name>
          <maml:uri />
        </dev:type>
        <dev:defaultValue>None</dev:defaultValue>
      </command:parameter>
      <command:parameter required="false" variableLength="true" globbing="false" pipelineInput="False" position="named" aliases="none">
        <maml:name>ProxyUseDefaultCredentials</maml:name>
        <maml:Description>
          <maml:para>Use the default credentials for the proxy</maml:para>
        </maml:Description>
        <command:parameterValue required="true" variableLength="false">System.Management.Automation.SwitchParameter</command:parameterValue>
        <dev:type>
          <maml:name>System.Management.Automation.SwitchParameter</maml:name>
          <maml:uri />
        </dev:type>
        <dev:defaultValue>False</dev:defaultValue>
      </command:parameter>
    </command:parameters>
    <command:inputTypes />
    <command:returnValues />
    <maml:alertSet>
      <maml:alert>
        <maml:para></maml:para>
      </maml:alert>
    </maml:alertSet>
    <command:examples>
      <command:example>
        <maml:title>-------------------------- Example 1 --------------------------</maml:title>
        <dev:code>PS C:\&gt; {{ Add example code here }}</dev:code>
        <dev:remarks>
          <maml:para>{{ Add example description here }}</maml:para>
        </dev:remarks>
      </command:example>
    </command:examples>
    <command:relatedLinks />
  </command:command>
  <command:command xmlns:maml="http://schemas.microsoft.com/maml/2004/10" xmlns:command="http://schemas.microsoft.com/maml/dev/command/2004/10" xmlns:dev="http://schemas.microsoft.com/maml/dev/2004/10" xmlns:MSHelp="http://msdn.microsoft.com/mshelp">
    <command:details>
      <command:name>Invoke-VmService</command:name>
      <command:verb>Invoke</command:verb>
      <command:noun>VmService</command:noun>
      <maml:description>
        <maml:para></maml:para>
      </maml:description>
    </command:details>
    <maml:description>
      <maml:para>{{Fill in the Description}}</maml:para>
    </maml:description>
    <command:syntax>
      <command:syntaxItem>
        <maml:name>Invoke-VmService</maml:name>
        <command:parameter required="false" variableLength="true" globbing="false" pipelineInput="False" position="named" aliases="none">
          <maml:name>Filter</maml:name>
          <maml:Description>
            <maml:para>The filter in FIQL syntax used for the results.</maml:para>
          </maml:Description>
          <command:parameterValue required="true" variableLength="false">System.String</command:parameterValue>
          <dev:type>
            <maml:name>System.String</maml:name>
            <maml:uri />
          </dev:type>
          <dev:defaultValue>None</dev:defaultValue>
        </command:parameter>
        <command:parameter required="false" variableLength="true" globbing="false" pipelineInput="False" position="named" aliases="none">
          <maml:name>HttpPipelineAppend</maml:name>
          <maml:Description>
            <maml:para>SendAsync Pipeline Steps to be appended to the front of the pipeline</maml:para>
          </maml:Description>
          <command:parameterValue required="true" variableLength="false">Microsoft.Rest.ClientRuntime.SendAsyncStep[]</command:parameterValue>
          <dev:type>
            <maml:name>Microsoft.Rest.ClientRuntime.SendAsyncStep[]</maml:name>
            <maml:uri />
          </dev:type>
          <dev:defaultValue>None</dev:defaultValue>
        </command:parameter>
        <command:parameter required="false" variableLength="true" globbing="false" pipelineInput="False" position="named" aliases="none">
          <maml:name>HttpPipelinePrepend</maml:name>
          <maml:Description>
            <maml:para>SendAsync Pipeline Steps to be prepended to the front of the pipeline</maml:para>
          </maml:Description>
          <command:parameterValue required="true" variableLength="false">Microsoft.Rest.ClientRuntime.SendAsyncStep[]</command:parameterValue>
          <dev:type>
            <maml:name>Microsoft.Rest.ClientRuntime.SendAsyncStep[]</maml:name>
            <maml:uri />
          </dev:type>
          <dev:defaultValue>None</dev:defaultValue>
        </command:parameter>
        <command:parameter required="false" variableLength="true" globbing="false" pipelineInput="False" position="named" aliases="none">
          <maml:name>Kind</maml:name>
          <maml:Description>
            <maml:para>The kind name</maml:para>
          </maml:Description>
          <command:parameterValue required="true" variableLength="false">System.String</command:parameterValue>
          <dev:type>
            <maml:name>System.String</maml:name>
            <maml:uri />
          </dev:type>
          <dev:defaultValue>None</dev:defaultValue>
        </command:parameter>
        <command:parameter required="false" variableLength="true" globbing="false" pipelineInput="False" position="named" aliases="none">
          <maml:name>Length</maml:name>
          <maml:Description>
            <maml:para>The number of records to retrieve relative to the offset</maml:para>
          </maml:Description>
          <command:parameterValue required="true" variableLength="false">System.Int32</command:parameterValue>
          <dev:type>
            <maml:name>System.Int32</maml:name>
            <maml:uri />
          </dev:type>
          <dev:defaultValue>0</dev:defaultValue>
        </command:parameter>
        <command:parameter required="false" variableLength="true" globbing="false" pipelineInput="False" position="named" aliases="none">
          <maml:name>Offset</maml:name>
          <maml:Description>
            <maml:para>Offset from the start of the entity list</maml:para>
          </maml:Description>
          <command:parameterValue required="true" variableLength="false">System.Int32</command:parameterValue>
          <dev:type>
            <maml:name>System.Int32</maml:name>
            <maml:uri />
          </dev:type>
          <dev:defaultValue>0</dev:defaultValue>
        </command:parameter>
        <command:parameter required="false" variableLength="true" globbing="false" pipelineInput="False" position="named" aliases="none">
          <maml:name>password</maml:name>
          <maml:Description>
            <maml:para>The password for authentication</maml:para>
          </maml:Description>
          <command:parameterValue required="true" variableLength="false">System.String</command:parameterValue>
          <dev:type>
            <maml:name>System.String</maml:name>
            <maml:uri />
          </dev:type>
          <dev:defaultValue>None</dev:defaultValue>
        </command:parameter>
        <command:parameter required="false" variableLength="true" globbing="false" pipelineInput="False" position="named" aliases="none">
          <maml:name>Proxy</maml:name>
          <maml:Description>
            <maml:para>The URI for the proxy server to use</maml:para>
          </maml:Description>
          <command:parameterValue required="true" variableLength="false">System.Uri</command:parameterValue>
          <dev:type>
            <maml:name>System.Uri</maml:name>
            <maml:uri />
          </dev:type>
          <dev:defaultValue>None</dev:defaultValue>
        </command:parameter>
        <command:parameter required="false" variableLength="true" globbing="false" pipelineInput="False" position="named" aliases="none">
          <maml:name>ProxyCredential</maml:name>
          <maml:Description>
            <maml:para>Credentials for a proxy server to use for the remote call</maml:para>
          </maml:Description>
          <command:parameterValue required="true" variableLength="false">System.Management.Automation.PSCredential</command:parameterValue>
          <dev:type>
            <maml:name>System.Management.Automation.PSCredential</maml:name>
            <maml:uri />
          </dev:type>
          <dev:defaultValue>None</dev:defaultValue>
        </command:parameter>
        <command:parameter required="false" variableLength="true" globbing="false" pipelineInput="False" position="named" aliases="none">
          <maml:name>ProxyUseDefaultCredentials</maml:name>
          <maml:Description>
            <maml:para>Use the default credentials for the proxy</maml:para>
          </maml:Description>
          <dev:type>
            <maml:name>System.Management.Automation.SwitchParameter</maml:name>
            <maml:uri />
          </dev:type>
          <dev:defaultValue>False</dev:defaultValue>
        </command:parameter>
        <command:parameter required="false" variableLength="true" globbing="false" pipelineInput="False" position="named" aliases="none">
          <maml:name>SortAttribute</maml:name>
          <maml:Description>
            <maml:para>The attribute to perform sort on</maml:para>
          </maml:Description>
          <command:parameterValue required="true" variableLength="false">System.String</command:parameterValue>
          <dev:type>
            <maml:name>System.String</maml:name>
            <maml:uri />
          </dev:type>
          <dev:defaultValue>None</dev:defaultValue>
        </command:parameter>
        <command:parameter required="false" variableLength="true" globbing="false" pipelineInput="False" position="named" aliases="none">
          <maml:name>SortOrder</maml:name>
          <maml:Description>
            <maml:para>The sort order in which results are returned</maml:para>
          </maml:Description>
          <command:parameterValue required="true" variableLength="false">System.String</command:parameterValue>
          <dev:type>
            <maml:name>System.String</maml:name>
            <maml:uri />
          </dev:type>
          <dev:defaultValue>None</dev:defaultValue>
        </command:parameter>
        <command:parameter required="false" variableLength="true" globbing="false" pipelineInput="False" position="named" aliases="none">
          <maml:name>username</maml:name>
          <maml:Description>
            <maml:para>The username for authentication</maml:para>
          </maml:Description>
          <command:parameterValue required="true" variableLength="false">System.String</command:parameterValue>
          <dev:type>
            <maml:name>System.String</maml:name>
            <maml:uri />
          </dev:type>
          <dev:defaultValue>None</dev:defaultValue>
        </command:parameter>
        <command:parameter required="false" variableLength="true" globbing="false" pipelineInput="False" position="named" aliases="cf">
          <maml:name>Confirm</maml:name>
          <maml:Description>
            <maml:para>Prompts you for confirmation before running the cmdlet.</maml:para>
          </maml:Description>
          <dev:type>
            <maml:name>System.Management.Automation.SwitchParameter</maml:name>
            <maml:uri />
          </dev:type>
          <dev:defaultValue>False</dev:defaultValue>
        </command:parameter>
        <command:parameter required="false" variableLength="true" globbing="false" pipelineInput="False" position="named" aliases="wi">
          <maml:name>WhatIf</maml:name>
          <maml:Description>
            <maml:para>Shows what would happen if the cmdlet runs. The cmdlet is not run.</maml:para>
          </maml:Description>
          <dev:type>
            <maml:name>System.Management.Automation.SwitchParameter</maml:name>
            <maml:uri />
          </dev:type>
          <dev:defaultValue>False</dev:defaultValue>
        </command:parameter>
      </command:syntaxItem>
      <command:syntaxItem>
        <maml:name>Invoke-VmService</maml:name>
        <command:parameter required="true" variableLength="true" globbing="false" pipelineInput="True (ByValue)" position="named" aliases="none">
          <maml:name>GetEntitiesRequest</maml:name>
          <maml:Description>
            <maml:para>All api calls that return a list will have this metadata block as input</maml:para>
          </maml:Description>
          <command:parameterValue required="true" variableLength="false">Sample.API.Models.IVmListMetadata</command:parameterValue>
          <dev:type>
            <maml:name>Sample.API.Models.IVmListMetadata</maml:name>
            <maml:uri />
          </dev:type>
          <dev:defaultValue>None</dev:defaultValue>
        </command:parameter>
        <command:parameter required="false" variableLength="true" globbing="false" pipelineInput="False" position="named" aliases="none">
          <maml:name>HttpPipelineAppend</maml:name>
          <maml:Description>
            <maml:para>SendAsync Pipeline Steps to be appended to the front of the pipeline</maml:para>
          </maml:Description>
          <command:parameterValue required="true" variableLength="false">Microsoft.Rest.ClientRuntime.SendAsyncStep[]</command:parameterValue>
          <dev:type>
            <maml:name>Microsoft.Rest.ClientRuntime.SendAsyncStep[]</maml:name>
            <maml:uri />
          </dev:type>
          <dev:defaultValue>None</dev:defaultValue>
        </command:parameter>
        <command:parameter required="false" variableLength="true" globbing="false" pipelineInput="False" position="named" aliases="none">
          <maml:name>HttpPipelinePrepend</maml:name>
          <maml:Description>
            <maml:para>SendAsync Pipeline Steps to be prepended to the front of the pipeline</maml:para>
          </maml:Description>
          <command:parameterValue required="true" variableLength="false">Microsoft.Rest.ClientRuntime.SendAsyncStep[]</command:parameterValue>
          <dev:type>
            <maml:name>Microsoft.Rest.ClientRuntime.SendAsyncStep[]</maml:name>
            <maml:uri />
          </dev:type>
          <dev:defaultValue>None</dev:defaultValue>
        </command:parameter>
        <command:parameter required="false" variableLength="true" globbing="false" pipelineInput="False" position="named" aliases="none">
          <maml:name>password</maml:name>
          <maml:Description>
            <maml:para>The password for authentication</maml:para>
          </maml:Description>
          <command:parameterValue required="true" variableLength="false">System.String</command:parameterValue>
          <dev:type>
            <maml:name>System.String</maml:name>
            <maml:uri />
          </dev:type>
          <dev:defaultValue>None</dev:defaultValue>
        </command:parameter>
        <command:parameter required="false" variableLength="true" globbing="false" pipelineInput="False" position="named" aliases="none">
          <maml:name>Proxy</maml:name>
          <maml:Description>
            <maml:para>The URI for the proxy server to use</maml:para>
          </maml:Description>
          <command:parameterValue required="true" variableLength="false">System.Uri</command:parameterValue>
          <dev:type>
            <maml:name>System.Uri</maml:name>
            <maml:uri />
          </dev:type>
          <dev:defaultValue>None</dev:defaultValue>
        </command:parameter>
        <command:parameter required="false" variableLength="true" globbing="false" pipelineInput="False" position="named" aliases="none">
          <maml:name>ProxyCredential</maml:name>
          <maml:Description>
            <maml:para>Credentials for a proxy server to use for the remote call</maml:para>
          </maml:Description>
          <command:parameterValue required="true" variableLength="false">System.Management.Automation.PSCredential</command:parameterValue>
          <dev:type>
            <maml:name>System.Management.Automation.PSCredential</maml:name>
            <maml:uri />
          </dev:type>
          <dev:defaultValue>None</dev:defaultValue>
        </command:parameter>
        <command:parameter required="false" variableLength="true" globbing="false" pipelineInput="False" position="named" aliases="none">
          <maml:name>ProxyUseDefaultCredentials</maml:name>
          <maml:Description>
            <maml:para>Use the default credentials for the proxy</maml:para>
          </maml:Description>
          <dev:type>
            <maml:name>System.Management.Automation.SwitchParameter</maml:name>
            <maml:uri />
          </dev:type>
          <dev:defaultValue>False</dev:defaultValue>
        </command:parameter>
        <command:parameter required="false" variableLength="true" globbing="false" pipelineInput="False" position="named" aliases="none">
          <maml:name>SkipSSL</maml:name>
          <maml:Description>
            <maml:para>Skip the ssl validation</maml:para>
          </maml:Description>
          <dev:type>
            <maml:name>System.Management.Automation.SwitchParameter</maml:name>
            <maml:uri />
          </dev:type>
          <dev:defaultValue>False</dev:defaultValue>
        </command:parameter>
        <command:parameter required="false" variableLength="true" globbing="false" pipelineInput="False" position="named" aliases="none">
          <maml:name>username</maml:name>
          <maml:Description>
            <maml:para>The username for authentication</maml:para>
          </maml:Description>
          <command:parameterValue required="true" variableLength="false">System.String</command:parameterValue>
          <dev:type>
            <maml:name>System.String</maml:name>
            <maml:uri />
          </dev:type>
          <dev:defaultValue>None</dev:defaultValue>
        </command:parameter>
        <command:parameter required="false" variableLength="true" globbing="false" pipelineInput="False" position="named" aliases="cf">
          <maml:name>Confirm</maml:name>
          <maml:Description>
            <maml:para>Prompts you for confirmation before running the cmdlet.</maml:para>
          </maml:Description>
          <dev:type>
            <maml:name>System.Management.Automation.SwitchParameter</maml:name>
            <maml:uri />
          </dev:type>
          <dev:defaultValue>False</dev:defaultValue>
        </command:parameter>
        <command:parameter required="false" variableLength="true" globbing="false" pipelineInput="False" position="named" aliases="wi">
          <maml:name>WhatIf</maml:name>
          <maml:Description>
            <maml:para>Shows what would happen if the cmdlet runs. The cmdlet is not run.</maml:para>
          </maml:Description>
          <dev:type>
            <maml:name>System.Management.Automation.SwitchParameter</maml:name>
            <maml:uri />
          </dev:type>
          <dev:defaultValue>False</dev:defaultValue>
        </command:parameter>
      </command:syntaxItem>
    </command:syntax>
    <command:parameters>
      <command:parameter required="false" variableLength="true" globbing="false" pipelineInput="False" position="named" aliases="none">
        <maml:name>Filter</maml:name>
        <maml:Description>
          <maml:para>The filter in FIQL syntax used for the results.</maml:para>
        </maml:Description>
        <command:parameterValue required="true" variableLength="false">System.String</command:parameterValue>
        <dev:type>
          <maml:name>System.String</maml:name>
          <maml:uri />
        </dev:type>
        <dev:defaultValue>None</dev:defaultValue>
      </command:parameter>
      <command:parameter required="true" variableLength="true" globbing="false" pipelineInput="True (ByValue)" position="named" aliases="none">
        <maml:name>GetEntitiesRequest</maml:name>
        <maml:Description>
          <maml:para>All api calls that return a list will have this metadata block as input</maml:para>
        </maml:Description>
        <command:parameterValue required="true" variableLength="false">Sample.API.Models.IVmListMetadata</command:parameterValue>
        <dev:type>
          <maml:name>Sample.API.Models.IVmListMetadata</maml:name>
          <maml:uri />
        </dev:type>
        <dev:defaultValue>None</dev:defaultValue>
      </command:parameter>
      <command:parameter required="false" variableLength="true" globbing="false" pipelineInput="False" position="named" aliases="none">
        <maml:name>HttpPipelineAppend</maml:name>
        <maml:Description>
          <maml:para>SendAsync Pipeline Steps to be appended to the front of the pipeline</maml:para>
        </maml:Description>
        <command:parameterValue required="true" variableLength="false">Microsoft.Rest.ClientRuntime.SendAsyncStep[]</command:parameterValue>
        <dev:type>
          <maml:name>Microsoft.Rest.ClientRuntime.SendAsyncStep[]</maml:name>
          <maml:uri />
        </dev:type>
        <dev:defaultValue>None</dev:defaultValue>
      </command:parameter>
      <command:parameter required="false" variableLength="true" globbing="false" pipelineInput="False" position="named" aliases="none">
        <maml:name>HttpPipelinePrepend</maml:name>
        <maml:Description>
          <maml:para>SendAsync Pipeline Steps to be prepended to the front of the pipeline</maml:para>
        </maml:Description>
        <command:parameterValue required="true" variableLength="false">Microsoft.Rest.ClientRuntime.SendAsyncStep[]</command:parameterValue>
        <dev:type>
          <maml:name>Microsoft.Rest.ClientRuntime.SendAsyncStep[]</maml:name>
          <maml:uri />
        </dev:type>
        <dev:defaultValue>None</dev:defaultValue>
      </command:parameter>
      <command:parameter required="false" variableLength="true" globbing="false" pipelineInput="False" position="named" aliases="none">
        <maml:name>Kind</maml:name>
        <maml:Description>
          <maml:para>The kind name</maml:para>
        </maml:Description>
        <command:parameterValue required="true" variableLength="false">System.String</command:parameterValue>
        <dev:type>
          <maml:name>System.String</maml:name>
          <maml:uri />
        </dev:type>
        <dev:defaultValue>None</dev:defaultValue>
      </command:parameter>
      <command:parameter required="false" variableLength="true" globbing="false" pipelineInput="False" position="named" aliases="none">
        <maml:name>Length</maml:name>
        <maml:Description>
          <maml:para>The number of records to retrieve relative to the offset</maml:para>
        </maml:Description>
        <command:parameterValue required="true" variableLength="false">System.Int32</command:parameterValue>
        <dev:type>
          <maml:name>System.Int32</maml:name>
          <maml:uri />
        </dev:type>
        <dev:defaultValue>0</dev:defaultValue>
      </command:parameter>
      <command:parameter required="false" variableLength="true" globbing="false" pipelineInput="False" position="named" aliases="none">
        <maml:name>Offset</maml:name>
        <maml:Description>
          <maml:para>Offset from the start of the entity list</maml:para>
        </maml:Description>
        <command:parameterValue required="true" variableLength="false">System.Int32</command:parameterValue>
        <dev:type>
          <maml:name>System.Int32</maml:name>
          <maml:uri />
        </dev:type>
        <dev:defaultValue>0</dev:defaultValue>
      </command:parameter>
      <command:parameter required="false" variableLength="true" globbing="false" pipelineInput="False" position="named" aliases="none">
        <maml:name>password</maml:name>
        <maml:Description>
          <maml:para>The password for authentication</maml:para>
        </maml:Description>
        <command:parameterValue required="true" variableLength="false">System.String</command:parameterValue>
        <dev:type>
          <maml:name>System.String</maml:name>
          <maml:uri />
        </dev:type>
        <dev:defaultValue>None</dev:defaultValue>
      </command:parameter>
      <command:parameter required="false" variableLength="true" globbing="false" pipelineInput="False" position="named" aliases="none">
        <maml:name>Proxy</maml:name>
        <maml:Description>
          <maml:para>The URI for the proxy server to use</maml:para>
        </maml:Description>
        <command:parameterValue required="true" variableLength="false">System.Uri</command:parameterValue>
        <dev:type>
          <maml:name>System.Uri</maml:name>
          <maml:uri />
        </dev:type>
        <dev:defaultValue>None</dev:defaultValue>
      </command:parameter>
      <command:parameter required="false" variableLength="true" globbing="false" pipelineInput="False" position="named" aliases="none">
        <maml:name>ProxyCredential</maml:name>
        <maml:Description>
          <maml:para>Credentials for a proxy server to use for the remote call</maml:para>
        </maml:Description>
        <command:parameterValue required="true" variableLength="false">System.Management.Automation.PSCredential</command:parameterValue>
        <dev:type>
          <maml:name>System.Management.Automation.PSCredential</maml:name>
          <maml:uri />
        </dev:type>
        <dev:defaultValue>None</dev:defaultValue>
      </command:parameter>
      <command:parameter required="false" variableLength="true" globbing="false" pipelineInput="False" position="named" aliases="none">
        <maml:name>ProxyUseDefaultCredentials</maml:name>
        <maml:Description>
          <maml:para>Use the default credentials for the proxy</maml:para>
        </maml:Description>
        <command:parameterValue required="true" variableLength="false">System.Management.Automation.SwitchParameter</command:parameterValue>
        <dev:type>
          <maml:name>System.Management.Automation.SwitchParameter</maml:name>
          <maml:uri />
        </dev:type>
        <dev:defaultValue>False</dev:defaultValue>
      </command:parameter>
      <command:parameter required="false" variableLength="true" globbing="false" pipelineInput="False" position="named" aliases="none">
        <maml:name>SkipSSL</maml:name>
        <maml:Description>
          <maml:para>Skip the ssl validation</maml:para>
        </maml:Description>
        <command:parameterValue required="true" variableLength="false">System.Management.Automation.SwitchParameter</command:parameterValue>
        <dev:type>
          <maml:name>System.Management.Automation.SwitchParameter</maml:name>
          <maml:uri />
        </dev:type>
        <dev:defaultValue>False</dev:defaultValue>
      </command:parameter>
      <command:parameter required="false" variableLength="true" globbing="false" pipelineInput="False" position="named" aliases="none">
        <maml:name>SortAttribute</maml:name>
        <maml:Description>
          <maml:para>The attribute to perform sort on</maml:para>
        </maml:Description>
        <command:parameterValue required="true" variableLength="false">System.String</command:parameterValue>
        <dev:type>
          <maml:name>System.String</maml:name>
          <maml:uri />
        </dev:type>
        <dev:defaultValue>None</dev:defaultValue>
      </command:parameter>
      <command:parameter required="false" variableLength="true" globbing="false" pipelineInput="False" position="named" aliases="none">
        <maml:name>SortOrder</maml:name>
        <maml:Description>
          <maml:para>The sort order in which results are returned</maml:para>
        </maml:Description>
        <command:parameterValue required="true" variableLength="false">System.String</command:parameterValue>
        <dev:type>
          <maml:name>System.String</maml:name>
          <maml:uri />
        </dev:type>
        <dev:defaultValue>None</dev:defaultValue>
      </command:parameter>
      <command:parameter required="false" variableLength="true" globbing="false" pipelineInput="False" position="named" aliases="none">
        <maml:name>username</maml:name>
        <maml:Description>
          <maml:para>The username for authentication</maml:para>
        </maml:Description>
        <command:parameterValue required="true" variableLength="false">System.String</command:parameterValue>
        <dev:type>
          <maml:name>System.String</maml:name>
          <maml:uri />
        </dev:type>
        <dev:defaultValue>None</dev:defaultValue>
      </command:parameter>
      <command:parameter required="false" variableLength="true" globbing="false" pipelineInput="False" position="named" aliases="cf">
        <maml:name>Confirm</maml:name>
        <maml:Description>
          <maml:para>Prompts you for confirmation before running the cmdlet.</maml:para>
        </maml:Description>
        <command:parameterValue required="true" variableLength="false">System.Management.Automation.SwitchParameter</command:parameterValue>
        <dev:type>
          <maml:name>System.Management.Automation.SwitchParameter</maml:name>
          <maml:uri />
        </dev:type>
        <dev:defaultValue>False</dev:defaultValue>
      </command:parameter>
      <command:parameter required="false" variableLength="true" globbing="false" pipelineInput="False" position="named" aliases="wi">
        <maml:name>WhatIf</maml:name>
        <maml:Description>
          <maml:para>Shows what would happen if the cmdlet runs. The cmdlet is not run.</maml:para>
        </maml:Description>
        <command:parameterValue required="true" variableLength="false">System.Management.Automation.SwitchParameter</command:parameterValue>
        <dev:type>
          <maml:name>System.Management.Automation.SwitchParameter</maml:name>
          <maml:uri />
        </dev:type>
        <dev:defaultValue>False</dev:defaultValue>
      </command:parameter>
    </command:parameters>
    <command:inputTypes />
    <command:returnValues />
    <maml:alertSet>
      <maml:alert>
        <maml:para></maml:para>
      </maml:alert>
    </maml:alertSet>
    <command:examples>
      <command:example>
        <maml:title>-------------------------- Example 1 --------------------------</maml:title>
        <dev:code>PS C:\&gt; {{ Add example code here }}</dev:code>
        <dev:remarks>
          <maml:para>{{ Add example description here }}</maml:para>
        </dev:remarks>
      </command:example>
    </command:examples>
    <command:relatedLinks />
  </command:command>
  <command:command xmlns:maml="http://schemas.microsoft.com/maml/2004/10" xmlns:command="http://schemas.microsoft.com/maml/dev/command/2004/10" xmlns:dev="http://schemas.microsoft.com/maml/dev/2004/10" xmlns:MSHelp="http://msdn.microsoft.com/mshelp">
    <command:details>
      <command:name>New-AccessControlPolicyListMetadataObject</command:name>
      <command:verb>New</command:verb>
      <command:noun>AccessControlPolicyListMetadataObject</command:noun>
      <maml:description>
        <maml:para></maml:para>
      </maml:description>
    </command:details>
    <maml:description>
      <maml:para>{{Fill in the Description}}</maml:para>
    </maml:description>
    <command:syntax>
      <command:syntaxItem>
        <maml:name>New-AccessControlPolicyListMetadataObject</maml:name>
        <command:parameter required="false" variableLength="true" globbing="false" pipelineInput="False" position="named" aliases="none">
          <maml:name>Filter</maml:name>
          <maml:Description>
            <maml:para>The filter in FIQL syntax used for the results.</maml:para>
          </maml:Description>
          <command:parameterValue required="true" variableLength="false">System.String</command:parameterValue>
          <dev:type>
            <maml:name>System.String</maml:name>
            <maml:uri />
          </dev:type>
          <dev:defaultValue>None</dev:defaultValue>
        </command:parameter>
        <command:parameter required="false" variableLength="true" globbing="false" pipelineInput="False" position="named" aliases="none">
          <maml:name>Kind</maml:name>
          <maml:Description>
            <maml:para>The kind name</maml:para>
          </maml:Description>
          <command:parameterValue required="true" variableLength="false">System.String</command:parameterValue>
          <dev:type>
            <maml:name>System.String</maml:name>
            <maml:uri />
          </dev:type>
          <dev:defaultValue>None</dev:defaultValue>
        </command:parameter>
        <command:parameter required="false" variableLength="true" globbing="false" pipelineInput="False" position="named" aliases="none">
          <maml:name>Length</maml:name>
          <maml:Description>
            <maml:para>The number of records to retrieve relative to the offset</maml:para>
          </maml:Description>
          <command:parameterValue required="true" variableLength="false">System.Int32</command:parameterValue>
          <dev:type>
            <maml:name>System.Int32</maml:name>
            <maml:uri />
          </dev:type>
          <dev:defaultValue>0</dev:defaultValue>
        </command:parameter>
        <command:parameter required="false" variableLength="true" globbing="false" pipelineInput="False" position="named" aliases="none">
          <maml:name>Offset</maml:name>
          <maml:Description>
            <maml:para>Offset from the start of the entity list</maml:para>
          </maml:Description>
          <command:parameterValue required="true" variableLength="false">System.Int32</command:parameterValue>
          <dev:type>
            <maml:name>System.Int32</maml:name>
            <maml:uri />
          </dev:type>
          <dev:defaultValue>0</dev:defaultValue>
        </command:parameter>
        <command:parameter required="false" variableLength="true" globbing="false" pipelineInput="False" position="named" aliases="none">
          <maml:name>SortAttribute</maml:name>
          <maml:Description>
            <maml:para>The attribute to perform sort on</maml:para>
          </maml:Description>
          <command:parameterValue required="true" variableLength="false">System.String</command:parameterValue>
          <dev:type>
            <maml:name>System.String</maml:name>
            <maml:uri />
          </dev:type>
          <dev:defaultValue>None</dev:defaultValue>
        </command:parameter>
      </command:syntaxItem>
    </command:syntax>
    <command:parameters>
      <command:parameter required="false" variableLength="true" globbing="false" pipelineInput="False" position="named" aliases="none">
        <maml:name>Filter</maml:name>
        <maml:Description>
          <maml:para>The filter in FIQL syntax used for the results.</maml:para>
        </maml:Description>
        <command:parameterValue required="true" variableLength="false">System.String</command:parameterValue>
        <dev:type>
          <maml:name>System.String</maml:name>
          <maml:uri />
        </dev:type>
        <dev:defaultValue>None</dev:defaultValue>
      </command:parameter>
      <command:parameter required="false" variableLength="true" globbing="false" pipelineInput="False" position="named" aliases="none">
        <maml:name>Kind</maml:name>
        <maml:Description>
          <maml:para>The kind name</maml:para>
        </maml:Description>
        <command:parameterValue required="true" variableLength="false">System.String</command:parameterValue>
        <dev:type>
          <maml:name>System.String</maml:name>
          <maml:uri />
        </dev:type>
        <dev:defaultValue>None</dev:defaultValue>
      </command:parameter>
      <command:parameter required="false" variableLength="true" globbing="false" pipelineInput="False" position="named" aliases="none">
        <maml:name>Length</maml:name>
        <maml:Description>
          <maml:para>The number of records to retrieve relative to the offset</maml:para>
        </maml:Description>
        <command:parameterValue required="true" variableLength="false">System.Int32</command:parameterValue>
        <dev:type>
          <maml:name>System.Int32</maml:name>
          <maml:uri />
        </dev:type>
        <dev:defaultValue>0</dev:defaultValue>
      </command:parameter>
      <command:parameter required="false" variableLength="true" globbing="false" pipelineInput="False" position="named" aliases="none">
        <maml:name>Offset</maml:name>
        <maml:Description>
          <maml:para>Offset from the start of the entity list</maml:para>
        </maml:Description>
        <command:parameterValue required="true" variableLength="false">System.Int32</command:parameterValue>
        <dev:type>
          <maml:name>System.Int32</maml:name>
          <maml:uri />
        </dev:type>
        <dev:defaultValue>0</dev:defaultValue>
      </command:parameter>
      <command:parameter required="false" variableLength="true" globbing="false" pipelineInput="False" position="named" aliases="none">
        <maml:name>SortAttribute</maml:name>
        <maml:Description>
          <maml:para>The attribute to perform sort on</maml:para>
        </maml:Description>
        <command:parameterValue required="true" variableLength="false">System.String</command:parameterValue>
        <dev:type>
          <maml:name>System.String</maml:name>
          <maml:uri />
        </dev:type>
        <dev:defaultValue>None</dev:defaultValue>
      </command:parameter>
    </command:parameters>
    <command:inputTypes />
    <command:returnValues />
    <maml:alertSet>
      <maml:alert>
        <maml:para></maml:para>
      </maml:alert>
    </maml:alertSet>
    <command:examples>
      <command:example>
        <maml:title>-------------------------- Example 1 --------------------------</maml:title>
        <dev:code>PS C:\&gt; {{ Add example code here }}</dev:code>
        <dev:remarks>
          <maml:para>{{ Add example description here }}</maml:para>
        </dev:remarks>
      </command:example>
    </command:examples>
    <command:relatedLinks />
  </command:command>
  <command:command xmlns:maml="http://schemas.microsoft.com/maml/2004/10" xmlns:command="http://schemas.microsoft.com/maml/dev/command/2004/10" xmlns:dev="http://schemas.microsoft.com/maml/dev/2004/10" xmlns:MSHelp="http://msdn.microsoft.com/mshelp">
    <command:details>
      <command:name>New-VmListMetadataObject</command:name>
      <command:verb>New</command:verb>
      <command:noun>VmListMetadataObject</command:noun>
      <maml:description>
        <maml:para></maml:para>
      </maml:description>
    </command:details>
    <maml:description>
      <maml:para>{{Fill in the Description}}</maml:para>
    </maml:description>
    <command:syntax>
      <command:syntaxItem>
        <maml:name>New-VmListMetadataObject</maml:name>
        <command:parameter required="false" variableLength="true" globbing="false" pipelineInput="False" position="named" aliases="none">
          <maml:name>Filter</maml:name>
          <maml:Description>
            <maml:para>The filter in FIQL syntax used for the results.</maml:para>
          </maml:Description>
          <command:parameterValue required="true" variableLength="false">System.String</command:parameterValue>
          <dev:type>
            <maml:name>System.String</maml:name>
            <maml:uri />
          </dev:type>
          <dev:defaultValue>None</dev:defaultValue>
        </command:parameter>
        <command:parameter required="false" variableLength="true" globbing="false" pipelineInput="False" position="named" aliases="none">
          <maml:name>Kind</maml:name>
          <maml:Description>
            <maml:para>The kind name</maml:para>
          </maml:Description>
          <command:parameterValue required="true" variableLength="false">System.String</command:parameterValue>
          <dev:type>
            <maml:name>System.String</maml:name>
            <maml:uri />
          </dev:type>
          <dev:defaultValue>None</dev:defaultValue>
        </command:parameter>
        <command:parameter required="false" variableLength="true" globbing="false" pipelineInput="False" position="named" aliases="none">
          <maml:name>Length</maml:name>
          <maml:Description>
            <maml:para>The number of records to retrieve relative to the offset</maml:para>
          </maml:Description>
          <command:parameterValue required="true" variableLength="false">System.Int32</command:parameterValue>
          <dev:type>
            <maml:name>System.Int32</maml:name>
            <maml:uri />
          </dev:type>
          <dev:defaultValue>0</dev:defaultValue>
        </command:parameter>
        <command:parameter required="false" variableLength="true" globbing="false" pipelineInput="False" position="named" aliases="none">
          <maml:name>Offset</maml:name>
          <maml:Description>
            <maml:para>Offset from the start of the entity list</maml:para>
          </maml:Description>
          <command:parameterValue required="true" variableLength="false">System.Int32</command:parameterValue>
          <dev:type>
            <maml:name>System.Int32</maml:name>
            <maml:uri />
          </dev:type>
          <dev:defaultValue>0</dev:defaultValue>
        </command:parameter>
        <command:parameter required="false" variableLength="true" globbing="false" pipelineInput="False" position="named" aliases="none">
          <maml:name>SortAttribute</maml:name>
          <maml:Description>
            <maml:para>The attribute to perform sort on</maml:para>
          </maml:Description>
          <command:parameterValue required="true" variableLength="false">System.String</command:parameterValue>
          <dev:type>
            <maml:name>System.String</maml:name>
            <maml:uri />
          </dev:type>
          <dev:defaultValue>None</dev:defaultValue>
        </command:parameter>
        <command:parameter required="false" variableLength="true" globbing="false" pipelineInput="False" position="named" aliases="none">
          <maml:name>SortOrder</maml:name>
          <maml:Description>
            <maml:para>The sort order in which results are returned</maml:para>
          </maml:Description>
          <command:parameterValue required="true" variableLength="false">System.String</command:parameterValue>
          <dev:type>
            <maml:name>System.String</maml:name>
            <maml:uri />
          </dev:type>
          <dev:defaultValue>None</dev:defaultValue>
        </command:parameter>
      </command:syntaxItem>
    </command:syntax>
    <command:parameters>
      <command:parameter required="false" variableLength="true" globbing="false" pipelineInput="False" position="named" aliases="none">
        <maml:name>Filter</maml:name>
        <maml:Description>
          <maml:para>The filter in FIQL syntax used for the results.</maml:para>
        </maml:Description>
        <command:parameterValue required="true" variableLength="false">System.String</command:parameterValue>
        <dev:type>
          <maml:name>System.String</maml:name>
          <maml:uri />
        </dev:type>
        <dev:defaultValue>None</dev:defaultValue>
      </command:parameter>
      <command:parameter required="false" variableLength="true" globbing="false" pipelineInput="False" position="named" aliases="none">
        <maml:name>Kind</maml:name>
        <maml:Description>
          <maml:para>The kind name</maml:para>
        </maml:Description>
        <command:parameterValue required="true" variableLength="false">System.String</command:parameterValue>
        <dev:type>
          <maml:name>System.String</maml:name>
          <maml:uri />
        </dev:type>
        <dev:defaultValue>None</dev:defaultValue>
      </command:parameter>
      <command:parameter required="false" variableLength="true" globbing="false" pipelineInput="False" position="named" aliases="none">
        <maml:name>Length</maml:name>
        <maml:Description>
          <maml:para>The number of records to retrieve relative to the offset</maml:para>
        </maml:Description>
        <command:parameterValue required="true" variableLength="false">System.Int32</command:parameterValue>
        <dev:type>
          <maml:name>System.Int32</maml:name>
          <maml:uri />
        </dev:type>
        <dev:defaultValue>0</dev:defaultValue>
      </command:parameter>
      <command:parameter required="false" variableLength="true" globbing="false" pipelineInput="False" position="named" aliases="none">
        <maml:name>Offset</maml:name>
        <maml:Description>
          <maml:para>Offset from the start of the entity list</maml:para>
        </maml:Description>
        <command:parameterValue required="true" variableLength="false">System.Int32</command:parameterValue>
        <dev:type>
          <maml:name>System.Int32</maml:name>
          <maml:uri />
        </dev:type>
        <dev:defaultValue>0</dev:defaultValue>
      </command:parameter>
      <command:parameter required="false" variableLength="true" globbing="false" pipelineInput="False" position="named" aliases="none">
        <maml:name>SortAttribute</maml:name>
        <maml:Description>
          <maml:para>The attribute to perform sort on</maml:para>
        </maml:Description>
        <command:parameterValue required="true" variableLength="false">System.String</command:parameterValue>
        <dev:type>
          <maml:name>System.String</maml:name>
          <maml:uri />
        </dev:type>
        <dev:defaultValue>None</dev:defaultValue>
      </command:parameter>
      <command:parameter required="false" variableLength="true" globbing="false" pipelineInput="False" position="named" aliases="none">
        <maml:name>SortOrder</maml:name>
        <maml:Description>
          <maml:para>The sort order in which results are returned</maml:para>
        </maml:Description>
        <command:parameterValue required="true" variableLength="false">System.String</command:parameterValue>
        <dev:type>
          <maml:name>System.String</maml:name>
          <maml:uri />
        </dev:type>
        <dev:defaultValue>None</dev:defaultValue>
      </command:parameter>
    </command:parameters>
    <command:inputTypes />
    <command:returnValues />
    <maml:alertSet>
      <maml:alert>
        <maml:para></maml:para>
      </maml:alert>
    </maml:alertSet>
    <command:examples>
      <command:example>
        <maml:title>-------------------------- Example 1 --------------------------</maml:title>
        <dev:code>PS C:\&gt; {{ Add example code here }}</dev:code>
        <dev:remarks>
          <maml:para>{{ Add example description here }}</maml:para>
        </dev:remarks>
      </command:example>
    </command:examples>
    <command:relatedLinks />
  </command:command>
</helpItems>